args_enum/__init__.py
args_enum/_base_classes.py
args_enum/_base_classes.pyi
args_enum/args.py
args_enum-0.1.0.dist-info/WHEEL
args_enum-0.1.0.dist-info/METADATA
args_enum-0.1.0.dist-info/RECORD
