Metadata-Version: 2.1
Name: args-enum
Version: 0.1.0
Summary: Use Enums as containers for command-line options.
Author: MKUltra-Violet
Author-email: clockworktux@gmail.com
Requires-Python: >=3.10,<4.0
Classifier: Programming Language :: Python :: 3
Classifier: Programming Language :: Python :: 3.10
Requires-Dist: poetry (>=1.2.1,<2.0.0)
